pyUsda/__init__.py
pyUsda/base.py
pyUsda/client.py
pyUsda/domain.py
pyUsda/enums.py
pyUsda-1.0.3.dist-info/LICENSE
pyUsda-1.0.3.dist-info/METADATA
pyUsda-1.0.3.dist-info/WHEEL
pyUsda-1.0.3.dist-info/top_level.txt
pyUsda-1.0.3.dist-info/RECORD
