Metadata-Version: 2.1
Name: pyUsda
Version: 1.0.3
Summary: Interface for accessing USDA's FDC API
Home-page: https://github.com/eghosa-eke/python-usda-fdc
Author: Eghosa Eke
Author-email: eghosaeke@gmail.com
License: GNU General Public License 3
Project-URL: Source Code, https://github.com/eghosa-eke/python-usda-fdc
Keywords: api usda fdc nutrition food
Platform: UNKNOWN
Classifier: Development Status :: 5 - Production/Stable
Classifier: License :: OSI Approved :: GNU General Public License v3 (GPLv3)
Classifier: Natural Language :: English
Classifier: Intended Audience :: Developers
Classifier: Programming Language :: Python :: 3
Classifier: Programming Language :: Python :: 3 :: Only
Classifier: Programming Language :: Python :: 3.4
Classifier: Programming Language :: Python :: 3.5
Classifier: Programming Language :: Python :: 3.6
Classifier: Programming Language :: Python :: 3.7
License-File: LICENSE
Requires-Dist: requests (>=2.22.0)
